<?xml version="1.0" encoding="UTF-8"?>
<actions>
        <action>
            <actionName>CUSTOM-deploy</actionName>
            <displayName>deploy</displayName>
            <goals>
                <goal>gae:deploy</goal>
                
            </goals>
        </action>
        <action>
            <actionName>CUSTOM-jasmine bdd</actionName>
            <displayName>jasmine bdd</displayName>
            <goals>
                <goal>jasmine:bdd</goal>
            </goals>
        </action>
        <action>
            <actionName>CUSTOM-rollback GAE</actionName>
            <displayName>rollback GAE</displayName>
            <goals>
                <goal>gae:rollback</goal>
            </goals>
        </action>
        <action>
            <actionName>debug</actionName>
            <packagings>
                <packaging>war</packaging>
                <packaging>ear</packaging>
                <packaging>ejb</packaging>
            </packagings>
            <goals>
                <goal>package</goal>
                <goal>appengine:devserver</goal>
            </goals>
            <properties>
                <netbeans.deploy.debugmode>true</netbeans.deploy.debugmode>
                <netbeans.deploy>false</netbeans.deploy>
            </properties>
        </action>
        
        
        
        
        
    </actions>
